[{"client_id": 5, "communication_round": 1, "epoch": 1, "accuracy": 0.1187}, {"client_id": 5, "communication_round": 2, "epoch": 1, "accuracy": 0.2922}, {"client_id": 5, "communication_round": 3, "epoch": 1, "accuracy": 0.3812}, {"client_id": 5, "communication_round": 4, "epoch": 1, "accuracy": 0.4094}, {"client_id": 5, "communication_round": 5, "epoch": 1, "accuracy": 0.4359}, {"client_id": 5, "communication_round": 6, "epoch": 1, "accuracy": 0.4453}, {"client_id": 5, "communication_round": 7, "epoch": 1, "accuracy": 0.4813}, {"client_id": 5, "communication_round": 8, "epoch": 1, "accuracy": 0.5047}, {"client_id": 5, "communication_round": 9, "epoch": 1, "accuracy": 0.5141}, {"client_id": 5, "communication_round": 10, "epoch": 1, "accuracy": 0.5391}, {"client_id": 5, "communication_round": 11, "epoch": 1, "accuracy": 0.5547}, {"client_id": 5, "communication_round": 12, "epoch": 1, "accuracy": 0.5594}, {"client_id": 5, "communication_round": 13, "epoch": 1, "accuracy": 0.5563}, {"client_id": 5, "communication_round": 14, "epoch": 1, "accuracy": 0.5594}, {"client_id": 5, "communication_round": 15, "epoch": 1, "accuracy": 0.5859}, {"client_id": 5, "communication_round": 16, "epoch": 1, "accuracy": 0.5938}, {"client_id": 5, "communication_round": 17, "epoch": 1, "accuracy": 0.6047}, {"client_id": 5, "communication_round": 18, "epoch": 1, "accuracy": 0.6141}, {"client_id": 5, "communication_round": 19, "epoch": 1, "accuracy": 0.6156}, {"client_id": 5, "communication_round": 20, "epoch": 1, "accuracy": 0.6125}, {"client_id": 5, "communication_round": 21, "epoch": 1, "accuracy": 0.6344}, {"client_id": 5, "communication_round": 22, "epoch": 1, "accuracy": 0.6328}]